streamlink_serverless/__init__.py
streamlink_serverless/py.typed
streamlink_serverless/_jsii/__init__.py
streamlink_serverless/_jsii/streamlink-serverless@0.0.70.jsii.tgz
streamlink_serverless-0.0.70.dist-info/LICENSE
streamlink_serverless-0.0.70.dist-info/METADATA
streamlink_serverless-0.0.70.dist-info/WHEEL
streamlink_serverless-0.0.70.dist-info/top_level.txt
streamlink_serverless-0.0.70.dist-info/RECORD
